ibpm/__init__.py
ibpm/client.py
ibpm/responses.py
ibpm_api_client-0.1.2.dist-info/METADATA
ibpm_api_client-0.1.2.dist-info/WHEEL
ibpm_api_client-0.1.2.dist-info/top_level.txt
ibpm_api_client-0.1.2.dist-info/RECORD
